django_modalds/.DS_Store
django_modalds/__init__.py
django_modalds/admin.py
django_modalds/apps.py
django_modalds/models.py
django_modalds/tests.py
django_modalds/views.py
django_modalds/migrations/0001_initial.py
django_modalds/migrations/0002_alter_type1_h2_alter_type1_link_text_and_more.py
django_modalds/migrations/__init__.py
django_modalds/static/popupds/.DS_Store
django_modalds/static/popupds/js/jquery-3.6.0.min.js
django_modalds/static/popupds/js/jquery.cookie.js
django_modalds/templates/django_modalds/modalds.html
django_modalds/templates/django_modalds/type1.html
django_modalds/templates/django_modalds/type2.html
django_modalds/templates/django_modalds/type3.html
django_modalds/templates/django_modalds/type4.html
django_modalds/templates/django_modalds/type5.html
django_modalds/templatetags/__init__.py
django_modalds/templatetags/django_modalds_tags.py
django_modalds-0.2.0.dist-info/LICENSE
django_modalds-0.2.0.dist-info/WHEEL
django_modalds-0.2.0.dist-info/METADATA
django_modalds-0.2.0.dist-info/RECORD
