Metadata-Version: 2.1
Name: django-modalds
Version: 0.2.0
Summary: One of the my demiansoft apps
Author-email: Hyungjin Kim <hj3415@gmail.com>
Classifier: License :: OSI Approved :: MIT License
Requires-Dist: Django >= 4.2.11
Requires-Dist: pillow >= 10.2.0
Project-URL: Home, https://www.demiansoft.com
